{
  "resolvedId": "virtual:nuxt:/Users/mmk/listen/listen-nuxt/.nuxt/routes.mjs",
  "transforms": [
    {
      "name": "virtual",
      "result": "import { default as index7Z3oq5bEFXMeta } from \"/Users/mmk/listen/listen-nuxt/pages/index.vue?macro=true\";\nimport { default as installbvK8lnizZRMeta } from \"/Users/mmk/listen/listen-nuxt/pages/install.vue?macro=true\";\nexport default [\n  {\n    name: index7Z3oq5bEFXMeta?.name ?? \"index\",\n    path: index7Z3oq5bEFXMeta?.path ?? \"/\",\n    meta: index7Z3oq5bEFXMeta || {},\n    alias: index7Z3oq5bEFXMeta?.alias || [],\n    redirect: index7Z3oq5bEFXMeta?.redirect,\n    component: () => import(\"/Users/mmk/listen/listen-nuxt/pages/index.vue\").then(m => m.default || m)\n  },\n  {\n    name: installbvK8lnizZRMeta?.name ?? \"install\",\n    path: installbvK8lnizZRMeta?.path ?? \"/install\",\n    meta: installbvK8lnizZRMeta || {},\n    alias: installbvK8lnizZRMeta?.alias || [],\n    redirect: installbvK8lnizZRMeta?.redirect,\n    component: () => import(\"/Users/mmk/listen/listen-nuxt/pages/install.vue\").then(m => m.default || m)\n  }\n]",
      "start": 1712416379396,
      "end": 1712416379396,
      "sourcemaps": null
    },
    {
      "name": "nuxt:layer-aliasing",
      "start": 1712416379396,
      "end": 1712416379396,
      "order": "pre"
    },
    {
      "name": "nuxt:server-devonly:transform",
      "start": 1712416379396,
      "end": 1712416379396,
      "order": "pre"
    },
    {
      "name": "nuxt:client-fallback-auto-id",
      "start": 1712416379396,
      "end": 1712416379396,
      "order": "pre"
    },
    {
      "name": "vite:css",
      "start": 1712416379396,
      "end": 1712416379396,
      "order": "normal"
    },
    {
      "name": "vite:esbuild",
      "start": 1712416379396,
      "end": 1712416379396,
      "order": "normal"
    },
    {
      "name": "vite:json",
      "start": 1712416379396,
      "end": 1712416379396,
      "order": "normal"
    },
    {
      "name": "vite:worker",
      "start": 1712416379396,
      "end": 1712416379396,
      "order": "normal"
    },
    {
      "name": "vite:vue",
      "start": 1712416379396,
      "end": 1712416379396,
      "order": "normal"
    },
    {
      "name": "vite:vue-jsx",
      "start": 1712416379396,
      "end": 1712416379396,
      "order": "normal"
    },
    {
      "name": "replace",
      "start": 1712416379396,
      "end": 1712416379396,
      "order": "normal"
    },
    {
      "name": "nuxt:remove-plugin-metadata",
      "start": 1712416379396,
      "end": 1712416379396,
      "order": "normal"
    },
    {
      "name": "nuxt:chunk-error",
      "start": 1712416379396,
      "end": 1712416379396,
      "order": "normal"
    },
    {
      "name": "nuxt:components:imports",
      "start": 1712416379396,
      "end": 1712416379396,
      "order": "normal"
    },
    {
      "name": "replace",
      "start": 1712416379396,
      "end": 1712416379396,
      "order": "normal"
    },
    {
      "name": "ssr-styles",
      "start": 1712416379396,
      "end": 1712416379396,
      "order": "normal"
    },
    {
      "name": "vite:define",
      "start": 1712416379396,
      "end": 1712416379396,
      "order": "normal"
    },
    {
      "name": "vite:css-post",
      "start": 1712416379396,
      "end": 1712416379396,
      "order": "normal"
    },
    {
      "name": "vite:build-html",
      "start": 1712416379396,
      "end": 1712416379396,
      "order": "normal"
    },
    {
      "name": "vite:worker-import-meta-url",
      "start": 1712416379396,
      "end": 1712416379396,
      "order": "normal"
    },
    {
      "name": "vite:asset-import-meta-url",
      "start": 1712416379396,
      "end": 1712416379396,
      "order": "normal"
    },
    {
      "name": "commonjs",
      "start": 1712416379396,
      "end": 1712416379396,
      "order": "normal"
    },
    {
      "name": "vite:dynamic-import-vars",
      "start": 1712416379396,
      "end": 1712416379396,
      "order": "normal"
    },
    {
      "name": "vite:import-glob",
      "start": 1712416379396,
      "end": 1712416379396,
      "order": "normal"
    },
    {
      "name": "nuxt:composable-keys",
      "start": 1712416379396,
      "end": 1712416379396,
      "order": "post"
    },
    {
      "name": "nuxt:imports-transform",
      "start": 1712416379396,
      "end": 1712416379397,
      "order": "post"
    },
    {
      "name": "unctx:transform",
      "start": 1712416379397,
      "end": 1712416379397,
      "order": "post"
    },
    {
      "name": "nuxt:pages-macros-transform",
      "start": 1712416379397,
      "end": 1712416379397,
      "order": "post"
    },
    {
      "name": "nuxt:runtime-paths-dep",
      "start": 1712416379397,
      "end": 1712416379397,
      "order": "post"
    },
    {
      "name": "nuxt:route-injection-plugin",
      "start": 1712416379397,
      "end": 1712416379397,
      "order": "post"
    },
    {
      "name": "nuxt:components-loader",
      "start": 1712416379397,
      "end": 1712416379397,
      "order": "post"
    },
    {
      "name": "nuxt:tree-shake-composables:transform",
      "start": 1712416379397,
      "end": 1712416379397,
      "order": "post"
    },
    {
      "name": "vite:build-import-analysis",
      "result": "import { __vitePreload } from \"\u0000vite/preload-helper.js\";import { default as index7Z3oq5bEFXMeta } from \"/Users/mmk/listen/listen-nuxt/pages/index.vue?macro=true\";\nimport { default as installbvK8lnizZRMeta } from \"/Users/mmk/listen/listen-nuxt/pages/install.vue?macro=true\";\nexport default [\n  {\n    name: index7Z3oq5bEFXMeta?.name ?? \"index\",\n    path: index7Z3oq5bEFXMeta?.path ?? \"/\",\n    meta: index7Z3oq5bEFXMeta || {},\n    alias: index7Z3oq5bEFXMeta?.alias || [],\n    redirect: index7Z3oq5bEFXMeta?.redirect,\n    component: () => __vitePreload(() => import(\"/Users/mmk/listen/listen-nuxt/pages/index.vue\"),__VITE_IS_MODERN__?\"__VITE_PRELOAD__\":void 0,import.meta.url).then(m => m.default || m)\n  },\n  {\n    name: installbvK8lnizZRMeta?.name ?? \"install\",\n    path: installbvK8lnizZRMeta?.path ?? \"/install\",\n    meta: installbvK8lnizZRMeta || {},\n    alias: installbvK8lnizZRMeta?.alias || [],\n    redirect: installbvK8lnizZRMeta?.redirect,\n    component: () => __vitePreload(() => import(\"/Users/mmk/listen/listen-nuxt/pages/install.vue\"),__VITE_IS_MODERN__?\"__VITE_PRELOAD__\":void 0,import.meta.url).then(m => m.default || m)\n  }\n]",
      "start": 1712416379397,
      "end": 1712416379397,
      "order": "normal",
      "sourcemaps": null
    },
    {
      "name": "vite:reporter",
      "start": 1712416379397,
      "end": 1712416379397,
      "order": "normal"
    }
  ]
}
